p4p/__init__.py
p4p/_gw.cpython-313-darwin.so
p4p/_p4p.cpython-313-darwin.so
p4p/disect.py
p4p/example.conf
p4p/gw.py
p4p/pvagw@.service
p4p/rpc.py
p4p/util.py
p4p/version.py
p4p/wrapper.py
p4p/asLib/__init__.py
p4p/asLib/lex.py
p4p/asLib/pvlist.py
p4p/asLib/yacc.py
p4p/client/Qt.py
p4p/client/__init__.py
p4p/client/asyncio.py
p4p/client/cli.py
p4p/client/cothread.py
p4p/client/raw.py
p4p/client/thread.py
p4p/nt/__init__.py
p4p/nt/common.py
p4p/nt/enum.py
p4p/nt/ndarray.py
p4p/nt/scalar.py
p4p/server/__init__.py
p4p/server/asyncio.py
p4p/server/cli.py
p4p/server/cothread.py
p4p/server/raw.py
p4p/server/thread.py
p4p/test/__init__.py
p4p/test/asynciotest.py
p4p/test/cothreadtest.py
p4p/test/qttest.py
p4p/test/test_asLib.py
p4p/test/test_asyncio.py
p4p/test/test_client_raw.py
p4p/test/test_client_thread.py
p4p/test/test_cothread.py
p4p/test/test_gw.py
p4p/test/test_nt.py
p4p/test/test_qt.py
p4p/test/test_rpc.py
p4p/test/test_server.py
p4p/test/test_sharedpv.py
p4p/test/test_type.py
p4p/test/test_value.py
p4p/test/utils.py
p4p-4.2.2.dist-info/licenses/LICENSE
p4p-4.2.2.dist-info/METADATA
p4p-4.2.2.dist-info/WHEEL
p4p-4.2.2.dist-info/entry_points.txt
p4p-4.2.2.dist-info/top_level.txt
p4p-4.2.2.dist-info/RECORD
