Metadata-Version: 2.4
Name: p4p
Version: 4.2.2
Summary: Python interface to PVAccess protocol client
Home-page: https://epics-base.github.io/p4p
Author: Michael Davidsaver
Author-email: mdavidsaver@gmail.com
License: BSD
Keywords: epics scada
Classifier: Development Status :: 5 - Production/Stable
Classifier: Programming Language :: Python :: 2.7
Classifier: Programming Language :: Python :: 3
Classifier: Programming Language :: Python :: Implementation :: CPython
Classifier: License :: OSI Approved :: BSD License
Classifier: Intended Audience :: Science/Research
Classifier: Topic :: Scientific/Engineering
Classifier: Topic :: Software Development :: Libraries
Classifier: Topic :: System :: Distributed Computing
Classifier: Operating System :: POSIX :: Linux
Classifier: Operating System :: MacOS
Classifier: Operating System :: Microsoft :: Windows
Requires-Python: >=2.7
License-File: LICENSE
Requires-Dist: epicscorelibs<7.0.10.99.1,>=7.0.10.99.0.0
Requires-Dist: pvxslibs<1.6.0a1,>=1.5.0
Requires-Dist: nose2>=0.8.0
Requires-Dist: ply
Requires-Dist: numpy>=1.7
Requires-Dist: numpy<3
Provides-Extra: qt
Requires-Dist: qtpy; extra == "qt"
Dynamic: author
Dynamic: author-email
Dynamic: classifier
Dynamic: description
Dynamic: description-content-type
Dynamic: home-page
Dynamic: keywords
Dynamic: license
Dynamic: license-file
Dynamic: provides-extra
Dynamic: requires-dist
Dynamic: requires-python
Dynamic: summary
